{
  "script": "search_non_square_center_v2_2_safe.py",
  "elapsed_seconds": 457.40434217453003,
  "config": {
    "max_root": 75000,
    "search_mode": "relaxed7",
    "center_mode": "non-square",
    "min_total": 7,
    "workers": 7,
    "reduce_workers": 4,
    "pass2_workers": 2,
    "recombine_workers": 5,
    "x_batch_size": 768,
    "shard_size": 10000000,
    "moduli": [
      127,
      131,
      137
    ],
    "min_offsets_exact": 4,
    "min_offsets_relaxed": 9,
    "primitive_only": true,
    "distinct_roots": true
  },
  "stats": {
    "offset_rows_written": 7451532,
    "x_done": 75000,
    "shards_touched": 674,
    "centers_seen": 772785,
    "centers_no_candidate": 772785,
    "reject_structural_bonus_too_low": 95,
    "shard_id": 106530,
    "merged_results": 0,
    "merged_duplicates": 0
  },
  "tmp_size_gb": 0.24721440859138966,
  "free_gb": 691.5969161987305,
  "out": "results\\raw\\b2_v2_3_structural_R75000_count9_11.csv"
}